<?xml version="1.0" encoding="utf-8" ?>
<dwsync>
<file name="arrow-next-hover-rtl.png" local="128360672360000000" remote="129491982000000000" testing="0" />
<file name="arrow-next-hover.png" local="127597643080000000" remote="129491982000000000" testing="0" />
<file name="arrow-next-rtl.png" local="128360672360000000" remote="129491982000000000" testing="0" />
<file name="arrow-next-visited-rtl.png" local="128360672360000000" remote="129491982000000000" testing="0" />
<file name="arrow-next-visited.png" local="127597643080000000" remote="129491982000000000" testing="0" />
<file name="arrow-next.png" local="127597643080000000" remote="129491982000000000" testing="0" />
<file name="arrow-prev-hover-rtl.png" local="128360672360000000" remote="129491982000000000" testing="0" />
<file name="arrow-prev-hover.png" local="127597643080000000" remote="129491982000000000" testing="0" />
<file name="arrow-prev-rtl.png" local="128360672360000000" remote="129491982000000000" testing="0" />
<file name="arrow-prev-visited-rtl.png" local="128360672360000000" remote="129491983200000000" testing="0" />
<file name="arrow-prev-visited.png" local="127597643080000000" remote="129491983800000000" testing="0" />
<file name="arrow-prev.png" local="127597643080000000" remote="129491983800000000" testing="0" />
<file name="arrow-up-hover.png" local="127597643080000000" remote="129491983800000000" testing="0" />
<file name="arrow-up-visited.png" local="127597643080000000" remote="129491983800000000" testing="0" />
<file name="arrow-up.png" local="127597643080000000" remote="129491983800000000" testing="0" />
<file name="background.png" local="127597643080000000" remote="129491983800000000" testing="0" />
<file name="block.tpl.php" local="128309495760000000" remote="129491983800000000" testing="0" />
<file name="box.tpl.php" local="128309495760000000" remote="129491983800000000" testing="0" />
<file name="comment.tpl.php" local="128439482640000000" remote="129491983800000000" testing="0" />
<file name="forum-container-rtl.jpg" local="128354471880000000" remote="129491983800000000" testing="0" />
<file name="forum-container.jpg" local="127597643080000000" remote="129491983800000000" testing="0" />
<file name="forum-link-rtl.png" local="128339225880000000" remote="129491983800000000" testing="0" />
<file name="forum-link.png" local="127597643080000000" remote="129491983800000000" testing="0" />
<file name="header-a.jpg" local="127597643080000000" remote="129491983800000000" testing="0" />
<file name="header-b-rtl.jpg" local="128339225880000000" remote="129491983800000000" testing="0" />
<file name="header-b.jpg" local="127597643080000000" remote="129491983800000000" testing="0" />
<file name="header-c.png" local="127597643080000000" remote="129491983800000000" testing="0" />
<file name="icon-block-rtl.png" local="128339225880000000" remote="129491983800000000" testing="0" />
<file name="icon-block.png" local="127597643080000000" remote="129491983800000000" testing="0" />
<file name="icon-comment-rtl.png" local="128354471880000000" remote="129491983800000000" testing="0" />
<file name="icon-comment.png" local="127597643080000000" remote="129491983800000000" testing="0" />
<file name="logo-active-rtl.jpg" local="128360672360000000" remote="129491983800000000" testing="0" />
<file name="logo-active.jpg" local="127597643080000000" remote="129491983800000000" testing="0" />
<file name="logo-background-rtl.jpg" local="128360672360000000" remote="129491983800000000" testing="0" />
<file name="logo-background.jpg" local="127597643080000000" remote="129491983800000000" testing="0" />
<file name="logo-hover-rtl.jpg" local="128360672360000000" remote="129491983800000000" testing="0" />
<file name="logo-hover.jpg" local="127597643080000000" remote="129491983800000000" testing="0" />
<file name="logo.png" local="127597643080000000" remote="129491983800000000" testing="0" />
<file name="node.tpl.php" local="128309495760000000" remote="129491983800000000" testing="0" />
<file name="page.tpl.php" local="128855240120000000" remote="129491983800000000" testing="0" />
<file name="pushbutton.info" local="129369213880000000" remote="129491983800000000" testing="0" />
<file name="screenshot.png" local="127597643080000000" remote="129491983800000000" testing="0" />
<file name="style-rtl.css" local="128457696260000000" remote="129491983800000000" testing="0" />
<file name="style.css" local="128428394660000000" remote="129491983800000000" testing="0" />
<file name="tabs-off-rtl.png" local="128360672360000000" remote="129491983800000000" testing="0" />
<file name="tabs-off.png" local="127597643080000000" remote="129491983800000000" testing="0" />
<file name="tabs-on-rtl.png" local="128360672360000000" remote="129491983800000000" testing="0" />
<file name="tabs-on.png" local="127597643080000000" remote="129491983800000000" testing="0" />
<file name="tabs-option-hover-rtl.png" local="128339225880000000" remote="129491983800000000" testing="0" />
<file name="tabs-option-hover.png" local="127597643080000000" remote="129491983800000000" testing="0" />
<file name="tabs-option-off-rtl.png" local="128339225880000000" remote="129491983800000000" testing="0" />
<file name="tabs-option-off.png" local="127597643080000000" remote="129491983800000000" testing="0" />
<file name="tabs-option-on.png" local="127597643080000000" remote="129491983800000000" testing="0" />
</dwsync>